[
  {
    "result": 1,
    "cur_unit": "AED",
    "ttb": "360.61",
    "tts": "367.9",
    "deal_bas_r": "364.26",
    "bkpr": "364",
    "yy_efee_r": "0",
    "ten_dd_efee_r": "0",
    "kftc_bkpr": "364",
    "kftc_deal_bas_r": "364.26",
    "cur_nm": "아랍에미리트 디르함"
  },
  {
    "result": 1,
    "cur_unit": "AUD",
    "ttb": "867.29",
    "tts": "884.82",
    "deal_bas_r": "876.06",
    "bkpr": "876",
    "yy_efee_r": "0",
    "ten_dd_efee_r": "0",
    "kftc_bkpr": "876",
    "kftc_deal_bas_r": "876.06",
    "cur_nm": "호주 달러"
  },
  {
    "result": 1,
    "cur_unit": "BHD",
    "ttb": "3,513.41",
    "tts": "3,584.38",
    "deal_bas_r": "3,548.9",
    "bkpr": "3,548",
    "yy_efee_r": "0",
    "ten_dd_efee_r": "0",
    "kftc_bkpr": "3,548",
    "kftc_deal_bas_r": "3,548.9",
    "cur_nm": "바레인 디나르"
  },
  {
    "result": 1,
    "cur_unit": "BND",
    "ttb": "985.61",
    "tts": "1,005.52",
    "deal_bas_r": "995.57",
    "bkpr": "995",
    "yy_efee_r": "0",
    "ten_dd_efee_r": "0",
    "kftc_bkpr": "995",
    "kftc_deal_bas_r": "995.57",
    "cur_nm": "브루나이 달러"
  },
  {
    "result": 1,
    "cur_unit": "CAD",
    "ttb": "979.34",
    "tts": "999.13",
    "deal_bas_r": "989.24",
    "bkpr": "989",
    "yy_efee_r": "0",
    "ten_dd_efee_r": "0",
    "kftc_bkpr": "989",
    "kftc_deal_bas_r": "989.24",
    "cur_nm": "캐나다 달러"
  },
  {
    "result": 1,
    "cur_unit": "CHF",
    "ttb": "1,501.55",
    "tts": "1,531.88",
    "deal_bas_r": "1,516.72",
    "bkpr": "1,516",
    "yy_efee_r": "0",
    "ten_dd_efee_r": "0",
    "kftc_bkpr": "1,516",
    "kftc_deal_bas_r": "1,516.72",
    "cur_nm": "스위스 프랑"
  },
  {
    "result": 1,
    "cur_unit": "CNH",
    "ttb": "183.77",
    "tts": "187.48",
    "deal_bas_r": "185.63",
    "bkpr": "185",
    "yy_efee_r": "0",
    "ten_dd_efee_r": "0",
    "kftc_bkpr": "185",
    "kftc_deal_bas_r": "185.63",
    "cur_nm": "위안화"
  },
  {
    "result": 1,
    "cur_unit": "DKK",
    "ttb": "192.05",
    "tts": "195.92",
    "deal_bas_r": "193.99",
    "bkpr": "193",
    "yy_efee_r": "0",
    "ten_dd_efee_r": "0",
    "kftc_bkpr": "193",
    "kftc_deal_bas_r": "193.99",
    "cur_nm": "덴마아크 크로네"
  },
  {
    "result": 1,
    "cur_unit": "EUR",
    "ttb": "1,431.54",
    "tts": "1,460.46",
    "deal_bas_r": "1,446",
    "bkpr": "1,446",
    "yy_efee_r": "0",
    "ten_dd_efee_r": "0",
    "kftc_bkpr": "1,446",
    "kftc_deal_bas_r": "1,446",
    "cur_nm": "유로"
  },
  {
    "result": 1,
    "cur_unit": "GBP",
    "ttb": "1,671.81",
    "tts": "1,705.58",
    "deal_bas_r": "1,688.7",
    "bkpr": "1,688",
    "yy_efee_r": "0",
    "ten_dd_efee_r": "0",
    "kftc_bkpr": "1,688",
    "kftc_deal_bas_r": "1,688.7",
    "cur_nm": "영국 파운드"
  },
  {
    "result": 1,
    "cur_unit": "HKD",
    "ttb": "169.35",
    "tts": "172.78",
    "deal_bas_r": "171.07",
    "bkpr": "171",
    "yy_efee_r": "0",
    "ten_dd_efee_r": "0",
    "kftc_bkpr": "171",
    "kftc_deal_bas_r": "171.07",
    "cur_nm": "홍콩 달러"
  },
  {
    "result": 1,
    "cur_unit": "IDR(100)",
    "ttb": "8.45",
    "tts": "8.62",
    "deal_bas_r": "8.54",
    "bkpr": "8",
    "yy_efee_r": "0",
    "ten_dd_efee_r": "0",
    "kftc_bkpr": "8",
    "kftc_deal_bas_r": "8.54",
    "cur_nm": "인도네시아 루피아"
  },
  {
    "result": 1,
    "cur_unit": "JPY(100)",
    "ttb": "883.27",
    "tts": "901.12",
    "deal_bas_r": "892.2",
    "bkpr": "892",
    "yy_efee_r": "0",
    "ten_dd_efee_r": "0",
    "kftc_bkpr": "892",
    "kftc_deal_bas_r": "892.2",
    "cur_nm": "일본 옌"
  },
  {
    "result": 1,
    "cur_unit": "KRW",
    "ttb": "0",
    "tts": "0",
    "deal_bas_r": "1",
    "bkpr": "1",
    "yy_efee_r": "0",
    "ten_dd_efee_r": "0",
    "kftc_bkpr": "1",
    "kftc_deal_bas_r": "1",
    "cur_nm": "한국 원"
  },
  {
    "result": 1,
    "cur_unit": "KWD",
    "ttb": "4,303.18",
    "tts": "4,390.11",
    "deal_bas_r": "4,346.65",
    "bkpr": "4,346",
    "yy_efee_r": "0",
    "ten_dd_efee_r": "0",
    "kftc_bkpr": "4,346",
    "kftc_deal_bas_r": "4,346.65",
    "cur_nm": "쿠웨이트 디나르"
  },
  {
    "result": 1,
    "cur_unit": "MYR",
    "ttb": "276.08",
    "tts": "281.65",
    "deal_bas_r": "278.87",
    "bkpr": "278",
    "yy_efee_r": "0",
    "ten_dd_efee_r": "0",
    "kftc_bkpr": "278",
    "kftc_deal_bas_r": "278.87",
    "cur_nm": "말레이지아 링기트"
  },
  {
    "result": 1,
    "cur_unit": "NOK",
    "ttb": "126.25",
    "tts": "128.8",
    "deal_bas_r": "127.53",
    "bkpr": "127",
    "yy_efee_r": "0",
    "ten_dd_efee_r": "0",
    "kftc_bkpr": "127",
    "kftc_deal_bas_r": "127.53",
    "cur_nm": "노르웨이 크로네"
  },
  {
    "result": 1,
    "cur_unit": "NZD",
    "ttb": "816.43",
    "tts": "832.92",
    "deal_bas_r": "824.68",
    "bkpr": "824",
    "yy_efee_r": "0",
    "ten_dd_efee_r": "0",
    "kftc_bkpr": "824",
    "kftc_deal_bas_r": "824.68",
    "cur_nm": "뉴질랜드 달러"
  },
  {
    "result": 1,
    "cur_unit": "SAR",
    "ttb": "353.17",
    "tts": "360.3",
    "deal_bas_r": "356.74",
    "bkpr": "356",
    "yy_efee_r": "0",
    "ten_dd_efee_r": "0",
    "kftc_bkpr": "356",
    "kftc_deal_bas_r": "356.74",
    "cur_nm": "사우디 리얄"
  },
  {
    "result": 1,
    "cur_unit": "SEK",
    "ttb": "127.8",
    "tts": "130.39",
    "deal_bas_r": "129.1",
    "bkpr": "129",
    "yy_efee_r": "0",
    "ten_dd_efee_r": "0",
    "kftc_bkpr": "129",
    "kftc_deal_bas_r": "129.1",
    "cur_nm": "스웨덴 크로나"
  },
  {
    "result": 1,
    "cur_unit": "SGD",
    "ttb": "985.61",
    "tts": "1,005.52",
    "deal_bas_r": "995.57",
    "bkpr": "995",
    "yy_efee_r": "0",
    "ten_dd_efee_r": "0",
    "kftc_bkpr": "995",
    "kftc_deal_bas_r": "995.57",
    "cur_nm": "싱가포르 달러"
  },
  {
    "result": 1,
    "cur_unit": "THB",
    "ttb": "36.78",
    "tts": "37.53",
    "deal_bas_r": "37.16",
    "bkpr": "37",
    "yy_efee_r": "0",
    "ten_dd_efee_r": "0",
    "kftc_bkpr": "37",
    "kftc_deal_bas_r": "37.16",
    "cur_nm": "태국 바트"
  },
  {
    "result": 1,
    "cur_unit": "USD",
    "ttb": "1,324.52",
    "tts": "1,351.27",
    "deal_bas_r": "1,337.9",
    "bkpr": "1,337",
    "yy_efee_r": "0",
    "ten_dd_efee_r": "0",
    "kftc_bkpr": "1,337",
    "kftc_deal_bas_r": "1,337.9",
    "cur_nm": "미국 달러"
  }
]